nb2hugo/__init__.py
nb2hugo/exporter.py
nb2hugo/writer.py
nb2hugo/preprocessors/__init__.py
nb2hugo/preprocessors/fixlatex.py
nb2hugo/preprocessors/frontmatter.py
nb2hugo/preprocessors/images.py
nb2hugo/preprocessors/raw.py
nb2hugo-0.1.4.data/scripts/nb2hugo
nb2hugo-0.1.4.dist-info/LICENSE.txt
nb2hugo-0.1.4.dist-info/METADATA
nb2hugo-0.1.4.dist-info/WHEEL
nb2hugo-0.1.4.dist-info/top_level.txt
nb2hugo-0.1.4.dist-info/RECORD
