Metadata-Version: 2.1
Name: nb2hugo
Version: 0.1.4
Summary: A Jupyter notebook to Hugo markdown converter
Home-page: http://github.com/vlunot/nb2hugo
Author: Vincent Lunot
Author-email: vlunot@gmail.com
License: MIT
Keywords: jupyter notebook hugo converter
Platform: UNKNOWN
Requires-Python: >=3.6
Requires-Dist: nbconvert
Requires-Dist: nbformat
Requires-Dist: traitlets
Requires-Dist: argparse
Requires-Dist: pytest
